sheep_lca/__init__.py
sheep_lca/database/__init__.py
sheep_lca/database/sheep_database.db
sheep_lca/lca.py
sheep_lca/resource_manager/__init__.py
sheep_lca/resource_manager/animal_data.py
sheep_lca/resource_manager/data_loader.py
sheep_lca/resource_manager/database_manager.py
sheep_lca/resource_manager/models.py
sheep_lca/resource_manager/sheep_lca_data_manager.py
sheep_lca-0.3.1.dist-info/LICENSE
sheep_lca-0.3.1.dist-info/METADATA
sheep_lca-0.3.1.dist-info/WHEEL
sheep_lca-0.3.1.dist-info/RECORD
